vvtools/__init__.py
vvtools/vgeometry.py
vvtools/vhelper.py
vvtools/vloger.py
vvtools-0.1.1.dist-info/licenses/LICENSE
vvtools-0.1.1.dist-info/METADATA
vvtools-0.1.1.dist-info/WHEEL
vvtools-0.1.1.dist-info/top_level.txt
vvtools-0.1.1.dist-info/RECORD
